dfbrowse/__init__.py
dfbrowse/browse_dataframe_csvs.py
dfbrowse/browser_utils.py
dfbrowse/chunk_search_utils.py
dfbrowse/dataframe_browser.py
dfbrowse/dataframe_browser_functions.py
dfbrowse/dataframe_utils.py
dfbrowse/func_core.py
dfbrowse/gui_debug.py
dfbrowse/ipython_cli.py
dfbrowse/ipython_main.py
dfbrowse/ipython_utils.py
dfbrowse/keybindings.py
dfbrowse/list_utils.py
dfbrowse/main.sh
dfbrowse/urwid_table_browser.py
dfbrowse/urwid_utils.py
dfbrowse-0.1.1.dist-info/LICENSE
dfbrowse-0.1.1.dist-info/METADATA
dfbrowse-0.1.1.dist-info/WHEEL
dfbrowse-0.1.1.dist-info/RECORD
