Metadata-Version: 2.1
Name: dfbrowse
Version: 0.1.1
Summary: 
Author: Peter Gaultney
Author-email: petergaultney@gmail.com
Requires-Python: >=3.8,<4.0
Classifier: Programming Language :: Python :: 3
Classifier: Programming Language :: Python :: 3.8
Classifier: Programming Language :: Python :: 3.9
Classifier: Programming Language :: Python :: 3.10
Classifier: Programming Language :: Python :: 3.11
Requires-Dist: numpy (>=1.0)
Requires-Dist: pandas (>=1.0)
Requires-Dist: urwid (>=2.0)
